backoff/__init__.py
backoff/_async.py
backoff/_common.py
backoff/_decorator.py
backoff/_jitter.py
backoff/_sync.py
backoff/_typing.py
backoff/_wait_gen.py
backoff/py.typed
backoff/types.py
re_engage-1.0.1.dist-info/LICENSE
re_engage-1.0.1.dist-info/METADATA
re_engage-1.0.1.dist-info/WHEEL
re_engage-1.0.1.dist-info/RECORD
