Metadata-Version: 2.1
Name: re-engage
Version: 1.0.1
Summary: Function decoration for backoff and retry, this is an active fork of the original backoff library
Home-page: https://github.com/mattseymour/re-engage
License: MIT
Keywords: retry,backoff,decorators
Author: Original - Bob Green
Author-email: rgreen@aquent.com
Requires-Python: >3.8.0,<=3.13.0
Classifier: Development Status :: 5 - Production/Stable
Classifier: Intended Audience :: Developers
Classifier: License :: OSI Approved :: MIT License
Classifier: Natural Language :: English
Classifier: Operating System :: OS Independent
Classifier: Programming Language :: Python
Classifier: Programming Language :: Python :: 3
Classifier: Programming Language :: Python :: 3.9
Classifier: Programming Language :: Python :: 3.10
Classifier: Programming Language :: Python :: 3.11
Classifier: Programming Language :: Python :: 3.12
Classifier: Programming Language :: Python :: 3.8
Classifier: Topic :: Internet :: WWW/HTTP
Classifier: Topic :: Software Development :: Libraries :: Python Modules
Classifier: Topic :: Utilities
Project-URL: Repository, https://github.com/mattseymour/re-engage
